<?xml version="1.0" encoding="UTF-8" standalone="yes"?>
<p:notes xmlns:a="http://schemas.openxmlformats.org/drawingml/2006/main" xmlns:r="http://schemas.openxmlformats.org/officeDocument/2006/relationships" xmlns:p="http://schemas.openxmlformats.org/presentationml/2006/main"><p:cSld><p:spTree><p:nvGrpSpPr><p:cNvPr id="1" name=""/><p:cNvGrpSpPr/><p:nvPr/></p:nvGrpSpPr><p:grpSpPr><a:xfrm><a:off x="0" y="0"/><a:ext cx="0" cy="0"/><a:chOff x="0" y="0"/><a:chExt cx="0" cy="0"/></a:xfrm></p:grpSpPr><p:sp><p:nvSpPr><p:cNvPr id="2" name="Folienbildplatzhalter 1"/><p:cNvSpPr><a:spLocks noGrp="1" noRot="1" noChangeAspect="1"/></p:cNvSpPr><p:nvPr><p:ph type="sldImg"/></p:nvPr></p:nvSpPr><p:spPr><a:xfrm><a:off x="-144463" y="390525"/><a:ext cx="7146926" cy="4019550"/></a:xfrm></p:spPr></p:sp><p:sp><p:nvSpPr><p:cNvPr id="3" name="Notizenplatzhalter 2"/><p:cNvSpPr><a:spLocks noGrp="1"/></p:cNvSpPr><p:nvPr><p:ph type="body" idx="1"/></p:nvPr></p:nvSpPr><p:spPr/><p:txBody><a:bodyPr><a:noAutofit/></a:bodyPr><a:lstStyle/><a:p><a:pPr marL="179319" indent="-179319" defTabSz="914043"><a:tabLst><a:tab pos="179319" algn="l"/></a:tabLst><a:defRPr/></a:pPr><a:r><a:rPr lang="en-US" sz="900" dirty="0"><a:solidFill><a:srgbClr val="002060"/></a:solidFill></a:rPr><a:t>There</a:t></a:r><a:r><a:rPr lang="en-US" sz="900" baseline="0" dirty="0"><a:solidFill><a:srgbClr val="002060"/></a:solidFill></a:rPr><a:t> are 5 main Categories breaking down into 16 Secure Operations Tracks. </a:t></a:r></a:p><a:p><a:pPr marL="179319" indent="-179319" defTabSz="914043"><a:tabLst><a:tab pos="179319" algn="l"/></a:tabLst><a:defRPr/></a:pPr><a:endParaRPr lang="en-US" sz="900" baseline="0" dirty="0"><a:solidFill><a:srgbClr val="002060"/></a:solidFill></a:endParaRPr></a:p><a:p><a:pPr marL="179319" indent="-179319" defTabSz="914043"><a:tabLst><a:tab pos="179319" algn="l"/></a:tabLst><a:defRPr/></a:pPr><a:r><a:rPr lang="en-US" sz="900" baseline="0" dirty="0"><a:solidFill><a:srgbClr val="002060"/></a:solidFill></a:rPr><a:t>These 16 Secure Operations Tracks </a:t></a:r><a:r><a:rPr lang="en-US" sz="900" dirty="0"><a:solidFill><a:srgbClr val="002060"/></a:solidFill></a:rPr><a:t>cover the following topics: </a:t></a:r></a:p><a:p><a:pPr marL="179319" indent="-179319" defTabSz="914043"><a:tabLst><a:tab pos="179319" algn="l"/></a:tabLst><a:defRPr/></a:pPr><a:endParaRPr lang="en-US" sz="900" dirty="0"><a:solidFill><a:srgbClr val="002060"/></a:solidFill></a:endParaRPr></a:p><a:p><a:pPr marL="179319" indent="-179319" defTabSz="914043"><a:tabLst><a:tab pos="179319" algn="l"/></a:tabLst><a:defRPr/></a:pPr><a:r><a:rPr lang="en-US" sz="900" b="1" u="sng" baseline="0" dirty="0"><a:solidFill><a:srgbClr val="002060"/></a:solidFill></a:rPr><a:t>Security Compliance</a:t></a:r></a:p><a:p><a:pPr marL="179319" indent="-179319" defTabSz="914043"><a:buFont typeface="Arial" panose="020B0604020202020204" pitchFamily="34" charset="0"/><a:buChar char="•"/><a:tabLst><a:tab pos="179319" algn="l"/></a:tabLst><a:defRPr/></a:pPr><a:r><a:rPr lang="en-US" sz="900" baseline="0" dirty="0"><a:solidFill><a:srgbClr val="002060"/></a:solidFill></a:rPr><a:t>Security Governance: Adopt and enforce security policies for your SAP landscape and systems and create and implement an SAP Security Baseline for your company or organization</a:t></a:r></a:p><a:p><a:pPr marL="179319" indent="-179319" defTabSz="914043"><a:buFont typeface="Arial" panose="020B0604020202020204" pitchFamily="34" charset="0"/><a:buChar char="•"/><a:tabLst><a:tab pos="179319" algn="l"/></a:tabLst><a:defRPr/></a:pPr><a:r><a:rPr lang="en-US" sz="900" baseline="0" dirty="0"><a:solidFill><a:srgbClr val="002060"/></a:solidFill></a:rPr><a:t>Audit: Ensure and verify the compliance of a company’s IT infrastructure and operation with internal and external guidelines</a:t></a:r></a:p><a:p><a:pPr marL="179319" indent="-179319" defTabSz="914043"><a:buFont typeface="Arial" panose="020B0604020202020204" pitchFamily="34" charset="0"/><a:buChar char="•"/><a:tabLst><a:tab pos="179319" algn="l"/></a:tabLst><a:defRPr/></a:pPr><a:r><a:rPr lang="en-US" sz="900" baseline="0" dirty="0"><a:solidFill><a:srgbClr val="002060"/></a:solidFill></a:rPr><a:t>Cloud Security: Ensure secure operation in cloud and outsourcing scenarios </a:t></a:r></a:p><a:p><a:pPr marL="179319" indent="-179319" defTabSz="914043"><a:buFont typeface="Arial" panose="020B0604020202020204" pitchFamily="34" charset="0"/><a:buChar char="•"/><a:tabLst><a:tab pos="179319" algn="l"/></a:tabLst><a:defRPr/></a:pPr><a:r><a:rPr lang="en-US" sz="900" baseline="0" dirty="0"><a:solidFill><a:srgbClr val="002060"/></a:solidFill></a:rPr><a:t>Emergency Concept: Prepare for and react to emergency situations </a:t></a:r></a:p><a:p><a:pPr marL="179319" indent="-179319" defTabSz="914043"><a:buFont typeface="Arial" panose="020B0604020202020204" pitchFamily="34" charset="0"/><a:buChar char="•"/><a:tabLst><a:tab pos="179319" algn="l"/></a:tabLst><a:defRPr/></a:pPr><a:endParaRPr lang="en-US" sz="900" baseline="0" dirty="0"><a:solidFill><a:srgbClr val="002060"/></a:solidFill></a:endParaRPr></a:p><a:p><a:pPr marL="179319" indent="-179319" defTabSz="914043"><a:tabLst><a:tab pos="179319" algn="l"/></a:tabLst><a:defRPr/></a:pPr><a:r><a:rPr lang="en-US" sz="900" b="1" u="sng" baseline="0" dirty="0"><a:solidFill><a:srgbClr val="002060"/></a:solidFill></a:rPr><a:t>Secure Operation</a:t></a:r></a:p><a:p><a:pPr marL="179319" indent="-179319" defTabSz="914043"><a:buFont typeface="Arial" panose="020B0604020202020204" pitchFamily="34" charset="0"/><a:buChar char="•"/><a:tabLst><a:tab pos="179319" algn="l"/></a:tabLst><a:defRPr/></a:pPr><a:r><a:rPr lang="en-US" sz="900" baseline="0" dirty="0"><a:solidFill><a:srgbClr val="002060"/></a:solidFill></a:rPr><a:t>Users and Authorizations: Manage IT users and authorizations including special users like administrators</a:t></a:r></a:p><a:p><a:pPr marL="179319" indent="-179319" defTabSz="914043"><a:buFont typeface="Arial" panose="020B0604020202020204" pitchFamily="34" charset="0"/><a:buChar char="•"/><a:tabLst><a:tab pos="179319" algn="l"/></a:tabLst><a:defRPr/></a:pPr><a:r><a:rPr lang="en-US" sz="900" baseline="0" dirty="0"><a:solidFill><a:srgbClr val="002060"/></a:solidFill></a:rPr><a:t>Authentication and Single Sign-On: Authenticate users properly – but only as often as really required</a:t></a:r></a:p><a:p><a:pPr marL="179319" indent="-179319" defTabSz="914043"><a:buFont typeface="Arial" panose="020B0604020202020204" pitchFamily="34" charset="0"/><a:buChar char="•"/><a:tabLst><a:tab pos="179319" algn="l"/></a:tabLst><a:defRPr/></a:pPr><a:r><a:rPr lang="en-US" sz="900" baseline="0" dirty="0"><a:solidFill><a:srgbClr val="002060"/></a:solidFill></a:rPr><a:t>Support Security: Resolve software incidents in a secure manner</a:t></a:r></a:p><a:p><a:pPr marL="179319" indent="-179319" defTabSz="914043"><a:buFont typeface="Arial" panose="020B0604020202020204" pitchFamily="34" charset="0"/><a:buChar char="•"/><a:tabLst><a:tab pos="179319" algn="l"/></a:tabLst><a:defRPr/></a:pPr><a:r><a:rPr lang="en-US" sz="900" baseline="0" dirty="0"><a:solidFill><a:srgbClr val="002060"/></a:solidFill></a:rPr><a:t>Security Review and Monitoring: Review and monitor the security of your SAP systems on a regular basis</a:t></a:r></a:p><a:p><a:pPr marL="179319" indent="-179319" defTabSz="914043"><a:buFont typeface="Arial" panose="020B0604020202020204" pitchFamily="34" charset="0"/><a:buChar char="•"/><a:tabLst><a:tab pos="179319" algn="l"/></a:tabLst><a:defRPr/></a:pPr><a:endParaRPr lang="en-US" sz="900" baseline="0" dirty="0"><a:solidFill><a:srgbClr val="002060"/></a:solidFill></a:endParaRPr></a:p><a:p><a:pPr marL="179319" indent="-179319" defTabSz="914043"><a:tabLst><a:tab pos="179319" algn="l"/></a:tabLst><a:defRPr/></a:pPr><a:r><a:rPr lang="en-US" sz="900" b="1" u="sng" baseline="0" dirty="0"><a:solidFill><a:srgbClr val="002060"/></a:solidFill></a:rPr><a:t>Secure Setup</a:t></a:r></a:p><a:p><a:pPr marL="179319" indent="-179319" defTabSz="914043"><a:buFont typeface="Arial" panose="020B0604020202020204" pitchFamily="34" charset="0"/><a:buChar char="•"/><a:tabLst><a:tab pos="179319" algn="l"/></a:tabLst><a:defRPr/></a:pPr><a:r><a:rPr lang="en-US" sz="900" baseline="0" dirty="0"><a:solidFill><a:srgbClr val="002060"/></a:solidFill></a:rPr><a:t>Secure Configuration: Establish and maintain a secure configuration of standard and custom business applications </a:t></a:r></a:p><a:p><a:pPr marL="179319" indent="-179319" defTabSz="914043"><a:buFont typeface="Arial" panose="020B0604020202020204" pitchFamily="34" charset="0"/><a:buChar char="•"/><a:tabLst><a:tab pos="179319" algn="l"/></a:tabLst><a:defRPr/></a:pPr><a:r><a:rPr lang="en-US" sz="900" baseline="0" dirty="0"><a:solidFill><a:srgbClr val="002060"/></a:solidFill></a:rPr><a:t>Communication Security: Utilize communication security measures available in your SAP software</a:t></a:r></a:p><a:p><a:pPr marL="179319" indent="-179319" defTabSz="914043"><a:buFont typeface="Arial" panose="020B0604020202020204" pitchFamily="34" charset="0"/><a:buChar char="•"/><a:tabLst><a:tab pos="179319" algn="l"/></a:tabLst><a:defRPr/></a:pPr><a:r><a:rPr lang="en-US" sz="900" baseline="0" dirty="0"><a:solidFill><a:srgbClr val="002060"/></a:solidFill></a:rPr><a:t>Data Security: Secure critical data beyond pure authorization protection</a:t></a:r></a:p><a:p><a:pPr marL="179319" indent="-179319" defTabSz="914043"><a:buFont typeface="Arial" panose="020B0604020202020204" pitchFamily="34" charset="0"/><a:buChar char="•"/><a:tabLst><a:tab pos="179319" algn="l"/></a:tabLst><a:defRPr/></a:pPr><a:endParaRPr lang="en-US" sz="900" baseline="0" dirty="0"><a:solidFill><a:srgbClr val="002060"/></a:solidFill></a:endParaRPr></a:p><a:p><a:pPr marL="179319" indent="-179319" defTabSz="914043"><a:tabLst><a:tab pos="179319" algn="l"/></a:tabLst><a:defRPr/></a:pPr><a:r><a:rPr lang="en-US" sz="900" b="1" u="sng" baseline="0" dirty="0"><a:solidFill><a:srgbClr val="002060"/></a:solidFill></a:rPr><a:t>Secure Code</a:t></a:r></a:p><a:p><a:pPr marL="179319" indent="-179319" defTabSz="914043"><a:buFont typeface="Arial" panose="020B0604020202020204" pitchFamily="34" charset="0"/><a:buChar char="•"/><a:tabLst><a:tab pos="179319" algn="l"/></a:tabLst><a:defRPr/></a:pPr><a:r><a:rPr lang="en-US" sz="900" baseline="0" dirty="0"><a:solidFill><a:srgbClr val="002060"/></a:solidFill></a:rPr><a:t>Security Maintenance of SAP Code: Establish an effective process to maintain the security of SAP delivered code</a:t></a:r></a:p><a:p><a:pPr marL="179319" indent="-179319" defTabSz="914043"><a:buFont typeface="Arial" panose="020B0604020202020204" pitchFamily="34" charset="0"/><a:buChar char="•"/><a:tabLst><a:tab pos="179319" algn="l"/></a:tabLst><a:defRPr/></a:pPr><a:r><a:rPr lang="en-US" sz="900" baseline="0" dirty="0"><a:solidFill><a:srgbClr val="002060"/></a:solidFill></a:rPr><a:t>Custom Code Security: Develop secure custom code and maintain the security of it</a:t></a:r></a:p><a:p><a:pPr marL="179319" indent="-179319" defTabSz="914043"><a:buFont typeface="Arial" panose="020B0604020202020204" pitchFamily="34" charset="0"/><a:buChar char="•"/><a:tabLst><a:tab pos="179319" algn="l"/></a:tabLst><a:defRPr/></a:pPr><a:endParaRPr lang="en-US" sz="900" baseline="0" dirty="0"><a:solidFill><a:srgbClr val="002060"/></a:solidFill></a:endParaRPr></a:p><a:p><a:pPr marL="179319" indent="-179319" defTabSz="914043"><a:tabLst><a:tab pos="179319" algn="l"/></a:tabLst><a:defRPr/></a:pPr><a:r><a:rPr lang="en-US" sz="900" b="1" u="sng" dirty="0"><a:solidFill><a:srgbClr val="002060"/></a:solidFill></a:rPr><a:t>Infrastructure</a:t></a:r><a:r><a:rPr lang="en-US" sz="900" b="1" u="sng" baseline="0" dirty="0"><a:solidFill><a:srgbClr val="002060"/></a:solidFill></a:rPr><a:t> Security</a:t></a:r></a:p><a:p><a:pPr marL="179319" indent="-179319" defTabSz="914043"><a:lnSpc><a:spcPct val="100000"/></a:lnSpc><a:spcBef><a:spcPts val="0"/></a:spcBef><a:spcAft><a:spcPts val="0"/></a:spcAft><a:buFont typeface="Arial" panose="020B0604020202020204" pitchFamily="34" charset="0"/><a:buChar char="•"/><a:tabLst><a:tab pos="179319" algn="l"/></a:tabLst><a:defRPr/></a:pPr><a:r><a:rPr lang="en-US" sz="900" baseline="0" dirty="0"><a:solidFill><a:srgbClr val="002060"/></a:solidFill></a:rPr><a:t>Network Security: Ensure a secure network environment covering SAP requirements</a:t></a:r></a:p><a:p><a:pPr marL="179319" indent="-179319" defTabSz="914043"><a:buFont typeface="Arial" panose="020B0604020202020204" pitchFamily="34" charset="0"/><a:buChar char="•"/><a:tabLst><a:tab pos="179319" algn="l"/></a:tabLst><a:defRPr/></a:pPr><a:r><a:rPr lang="en-US" sz="900" baseline="0" dirty="0"><a:solidFill><a:srgbClr val="002060"/></a:solidFill></a:rPr><a:t>Operating System and Database Security: Cover SAP requirements towards the OS and DB level</a:t></a:r></a:p><a:p><a:pPr marL="179319" indent="-179319" defTabSz="914043"><a:buFont typeface="Arial" panose="020B0604020202020204" pitchFamily="34" charset="0"/><a:buChar char="•"/><a:tabLst><a:tab pos="179319" algn="l"/></a:tabLst><a:defRPr/></a:pPr><a:r><a:rPr lang="en-US" sz="900" baseline="0" dirty="0"><a:solidFill><a:srgbClr val="002060"/></a:solidFill></a:rPr><a:t>Frontend Security: Establish proper security on the frontend including workstations and mobile devices</a:t></a:r></a:p><a:p><a:pPr marL="179319" indent="-179319" defTabSz="914043"><a:buFont typeface="Arial" panose="020B0604020202020204" pitchFamily="34" charset="0"/><a:buChar char="•"/><a:tabLst><a:tab pos="179319" algn="l"/></a:tabLst><a:defRPr/></a:pPr><a:endParaRPr lang="en-US" sz="900" baseline="0" dirty="0"><a:solidFill><a:srgbClr val="002060"/></a:solidFill></a:endParaRPr></a:p></p:txBody></p:sp><p:sp><p:nvSpPr><p:cNvPr id="4" name="Foliennummernplatzhalter 3"/><p:cNvSpPr><a:spLocks noGrp="1"/></p:cNvSpPr><p:nvPr><p:ph type="sldNum" sz="quarter" idx="10"/></p:nvPr></p:nvSpPr><p:spPr/><p:txBody><a:bodyPr/><a:lstStyle/><a:p><a:fld id="{7D8C2C35-2B8A-446E-BEC0-FD36716C29AC}" type="slidenum"><a:rPr lang="de-DE" smtClean="0"/><a:pPr/><a:t>11</a:t></a:fld><a:endParaRPr lang="de-DE" dirty="0"/></a:p></p:txBody></p:sp></p:spTree><p:extLst><p:ext uri="{BB962C8B-B14F-4D97-AF65-F5344CB8AC3E}"><p14:creationId xmlns:p14="http://schemas.microsoft.com/office/powerpoint/2010/main" val="1855344722"/></p:ext></p:extLst></p:cSld><p:clrMapOvr><a:masterClrMapping/></p:clrMapOvr></p:notes>